email_assistant/assistant.py
email_assistant/iata.py
email_assistant/plugin.py
email_assistant/plugins/__init__.py
email_assistant/plugins/eventbrite.py
email_assistant/plugins/general.py
email_assistant/plugins/marriott.py
email_assistant/plugins/united.py
email_assistant-0.0.0.dist-info/AUTHORS
email_assistant-0.0.0.dist-info/COPYING
email_assistant-0.0.0.dist-info/METADATA
email_assistant-0.0.0.dist-info/WHEEL
email_assistant-0.0.0.dist-info/entry_points.txt
email_assistant-0.0.0.dist-info/pbr.json
email_assistant-0.0.0.dist-info/top_level.txt
email_assistant-0.0.0.dist-info/RECORD
