Metadata-Version: 2.1
Name: email-assistant
Version: 0.0.0
Summary: Add entries to caldav servers based on email contents
Home-page: UNKNOWN
Author: James E. Blair
Author-email: corvus@gnu.org
License: UNKNOWN
Platform: UNKNOWN
Classifier: Intended Audience :: Information Technology
Classifier: Intended Audience :: System Administrators
Classifier: Intended Audience :: End Users/Desktop
Classifier: License :: OSI Approved :: GNU Affero General Public License v3 or later (AGPLv3+)
Classifier: Programming Language :: Python
Classifier: Programming Language :: Python :: 3
Classifier: Programming Language :: Python :: 3.5
Classifier: Topic :: Communications :: Email
Classifier: Topic :: Office/Business :: Scheduling
Requires-Python: >=3.5
Requires-Dist: pbr
Requires-Dist: BeautifulSoup4
Requires-Dist: geopy
Requires-Dist: timezonefinder
Requires-Dist: caldav
Requires-Dist: python-dateutil
Requires-Dist: inscriptis
Requires-Dist: vobject
